genstudio/__init__.py
genstudio/chrome_devtools.py
genstudio/components/__init__.py
genstudio/components/bitmap.py
genstudio/docs/plugin.py
genstudio/env.py
genstudio/html.py
genstudio/js/api.jsx
genstudio/js/binary.ts
genstudio/js/canvasSnapshot.ts
genstudio/js/components/bitmap.tsx
genstudio/js/context.ts
genstudio/js/eval.js
genstudio/js/globals.js
genstudio/js/import-map.cdn.json
genstudio/js/layout.jsx
genstudio/js/markdown-it-katex.js
genstudio/js/plot/ellipse.js
genstudio/js/plot/events.js
genstudio/js/plot/img.js
genstudio/js/plot/pixels.js
genstudio/js/plot/render.js
genstudio/js/plot/style.js
genstudio/js/plot.jsx
genstudio/js/ready.ts
genstudio/js/scene3d/camera3d.ts
genstudio/js/scene3d/components/ring.ts
genstudio/js/scene3d/components.ts
genstudio/js/scene3d/fps.tsx
genstudio/js/scene3d/geometry.ts
genstudio/js/scene3d/impl3d.tsx
genstudio/js/scene3d/picking.ts
genstudio/js/scene3d/quaternion.ts
genstudio/js/scene3d/scene3d.tsx
genstudio/js/scene3d/shaders.ts
genstudio/js/scene3d/types.ts
genstudio/js/utils.ts
genstudio/js/widget.jsx
genstudio/js/widget_build.js
genstudio/layout.py
genstudio/plot.py
genstudio/plot_defs.py
genstudio/plot_spec.py
genstudio/scene3d.py
genstudio/screenshots.py
genstudio/scripts/css_modifier.py
genstudio/scripts/make_observable_plot_defs.py
genstudio/scripts/observable_plot_metadata.js
genstudio/scripts/observable_plot_metadata.json
genstudio/scripts/package.json
genstudio/scripts/tailwind_builder.py
genstudio/scripts/yarn.lock
genstudio/util.py
genstudio/widget.css
genstudio/widget.py
genstudio-2025.4.1.dist-info/LICENSE
genstudio-2025.4.1.dist-info/METADATA
genstudio-2025.4.1.dist-info/WHEEL
genstudio-2025.4.1.dist-info/entry_points.txt
genstudio-2025.4.1.dist-info/RECORD
