Metadata-Version: 2.3
Name: genstudio
Version: 2025.4.1
Summary: 
License: MIT
Author: Matthew Huebert
Author-email: me@matt.is
Requires-Python: >=3.10,<4.0
Classifier: License :: OSI Approved :: MIT License
Classifier: Programming Language :: Python :: 3
Classifier: Programming Language :: Python :: 3.10
Classifier: Programming Language :: Python :: 3.11
Classifier: Programming Language :: Python :: 3.12
Classifier: Programming Language :: Python :: 3.13
Requires-Dist: anywidget (>=0.9.10,<0.10.0)
Requires-Dist: traitlets (>=5.14.3,<6.0.0)
Requires-Dist: websockets (>=15.0,<16.0)
